S3Backup/__init__.py
S3Backup/config_loader.py
S3Backup/hash_file.py
S3Backup/plan.py
S3Backup-0.12.dist-info/AUTHORS
S3Backup-0.12.dist-info/LICENSE
S3Backup-0.12.dist-info/METADATA
S3Backup-0.12.dist-info/WHEEL
S3Backup-0.12.dist-info/top_level.txt
S3Backup-0.12.dist-info/RECORD
