Metadata-Version: 2.1
Name: S3Backup
Version: 0.12
Summary: Perform scripted backups to Amazon S3
Home-page: https://github.com/mgoodfellow/s3-backup
Author: Mike Goodfellow
Author-email: mdgoodfellow@gmail.com
License: MIT
Keywords: backup,aws,s3
License-File: LICENSE
License-File: AUTHORS
Requires-Dist: boto3
Requires-Dist: glob2
